tests/__init__.py
tests/test_advanced_math.py
tests/test_algorithm.py
tests/test_basic_math.py
utils/__init__.py
utils/advanced_math.py
utils/algorithm.py
utils/basic_math.py
MathZenith-0.1.dist-info/METADATA
MathZenith-0.1.dist-info/WHEEL
MathZenith-0.1.dist-info/top_level.txt
MathZenith-0.1.dist-info/RECORD
