Metadata-Version: 2.1
Name: MathZenith
Version: 0.1
Summary: A package for basic and advanced math operations and sorting/searching algorithms.
Home-page: https://github.com/yourusername/mathutils
Author: I235678
Author-email: i235678@nu.edu.pk
License: MIT
Keywords: math algorithms
